Metadata-Version: 2.1
Name: cuml-cu13
Version: 25.12.0
Summary: cuML - RAPIDS ML Algorithms
Author: NVIDIA Corporation
License: Apache-2.0
Classifier: Intended Audience :: Developers
Classifier: Programming Language :: Python
Classifier: Programming Language :: Python :: 3.10
Classifier: Programming Language :: Python :: 3.11
Classifier: Programming Language :: Python :: 3.12
Project-URL: Homepage, https://github.com/rapidsai/cuml
Project-URL: Documentation, https://docs.rapids.ai/api/cuml/stable/
Requires-Python: >=3.10
Requires-Dist: cuda-python<14.0a0,>=13.0.1
Requires-Dist: cuda-toolkit[cublas,cufft,curand,cusolver,cusparse]==13.*
Requires-Dist: cudf-cu13==25.12.*
Requires-Dist: cupy-cuda13x>=13.6.0
Requires-Dist: joblib>=0.11
Requires-Dist: libcuml-cu13==25.12.*
Requires-Dist: numba-cuda[cu13]<0.20.0a0,>=0.19.1
Requires-Dist: numba<0.62.0a0,>=0.60.0
Requires-Dist: numpy<3.0a0,>=1.23
Requires-Dist: packaging
Requires-Dist: pylibraft-cu13==25.12.*
Requires-Dist: rich
Requires-Dist: rmm-cu13==25.12.*
Requires-Dist: scikit-learn>=1.4
Requires-Dist: scipy>=1.11.0
Requires-Dist: treelite<5.0.0a0,>=4.6.1
Provides-Extra: test
Requires-Dist: certifi; extra == "test"
Requires-Dist: cython<3.2.0a0,>=3.0.0; extra == "test"
Requires-Dist: hdbscan<0.8.40,>=0.8.39; extra == "test"
Requires-Dist: hypothesis<7,>=6.0; extra == "test"
Requires-Dist: nltk; extra == "test"
Requires-Dist: numpydoc<1.9; extra == "test"
Requires-Dist: nvidia-ml-py>=12; extra == "test"
Requires-Dist: pynndescent; extra == "test"
Requires-Dist: pytest-benchmark; extra == "test"
Requires-Dist: pytest-cases; extra == "test"
Requires-Dist: pytest-cov; extra == "test"
Requires-Dist: pytest-xdist; extra == "test"
Requires-Dist: pytest<9.0; extra == "test"
Requires-Dist: pyyaml; extra == "test"
Requires-Dist: scikit-learn<1.8.0,>=1.4; extra == "test"
Requires-Dist: seaborn; extra == "test"
Requires-Dist: statsmodels; extra == "test"
Requires-Dist: tenacity; extra == "test"
Requires-Dist: umap-learn==0.5.7; extra == "test"
Requires-Dist: xgboost>=2.1.0; extra == "test"
Provides-Extra: dask
Requires-Dist: dask-cudf-cu13==25.12.*; extra == "dask"
Requires-Dist: raft-dask-cu13==25.12.*; extra == "dask"
Requires-Dist: rapids-dask-dependency==25.12.*; extra == "dask"
Provides-Extra: test-dask
Requires-Dist: dask-cuda==25.12.*; extra == "test-dask"
Requires-Dist: dask-ml; extra == "test-dask"
